{
  "tags": null,
  "ignoreAlpha": false,
  "maxSimultaneousLights": 4,
  "forceAlphaBlending": false,
  "mode": 0,
  "id": "NM_CarPaint",
  "uniqueId": 142735,
  "name": "NM_CarPaint",
  "checkReadyOnEveryCall": false,
  "checkReadyOnlyOnce": false,
  "state": "",
  "alpha": 1,
  "backFaceCulling": true,
  "cullBackFaces": true,
  "sideOrientation": 1,
  "alphaMode": 2,
  "_needDepthPrePass": false,
  "disableDepthWrite": false,
  "disableColorWrite": false,
  "forceDepthWrite": false,
  "depthFunction": 0,
  "separateCullingPass": false,
  "fogEnabled": true,
  "pointSize": 1,
  "zOffset": 0,
  "zOffsetUnits": 0,
  "pointsCloud": false,
  "fillMode": 0,
  "editorData": {
    "locations": [
      {
        "blockId": 165758,
        "x": -820,
        "y": 660
      },
      {
        "blockId": 165759,
        "x": -1080,
        "y": 660
      },
      {
        "blockId": 165760,
        "x": -1120,
        "y": 1060
      },
      {
        "blockId": 165761,
        "x": -1620,
        "y": 660
      },
      {
        "blockId": 165762,
        "x": -1720,
        "y": 760
      },
      {
        "blockId": 165763,
        "x": -1420,
        "y": 660
      },
      {
        "blockId": 165764,
        "x": 5080,
        "y": 880
      },
      {
        "blockId": 165765,
        "x": 4880,
        "y": 880
      },
      {
        "blockId": 165766,
        "x": 4620,
        "y": 960
      },
      {
        "blockId": 165767,
        "x": 3400,
        "y": 700
      },
      {
        "blockId": 165768,
        "x": -1420,
        "y": 960
      },
      {
        "blockId": 165769,
        "x": -2120,
        "y": 860
      },
      {
        "blockId": 165770,
        "x": 200,
        "y": 1000
      },
      {
        "blockId": 165771,
        "x": -1420,
        "y": 760
      },
      {
        "blockId": 165772,
        "x": -1720,
        "y": 860
      },
      {
        "blockId": 165773,
        "x": 3200,
        "y": 100
      },
      {
        "blockId": 165774,
        "x": 480,
        "y": 120
      },
      {
        "blockId": 165775,
        "x": -1520,
        "y": 1060
      },
      {
        "blockId": 165776,
        "x": -1720,
        "y": 1160
      },
      {
        "blockId": 165777,
        "x": -320,
        "y": 320
      },
      {
        "blockId": 165778,
        "x": 180,
        "y": 220
      },
      {
        "blockId": 165780,
        "x": -120,
        "y": 220
      },
      {
        "blockId": 165781,
        "x": -320,
        "y": 220
      },
      {
        "blockId": 165782,
        "x": 160,
        "y": 520
      },
      {
        "blockId": 165783,
        "x": 2420,
        "y": -840
      },
      {
        "blockId": 165784,
        "x": 2120,
        "y": -960
      },
      {
        "blockId": 165785,
        "x": 2120,
        "y": -860
      },
      {
        "blockId": 165786,
        "x": 2100,
        "y": -760
      },
      {
        "blockId": 165787,
        "x": 300,
        "y": 1500
      },
      {
        "blockId": 165788,
        "x": 300,
        "y": 1500
      },
      {
        "blockId": 165789,
        "x": -1220,
        "y": 960
      },
      {
        "blockId": 165790,
        "x": 1600,
        "y": -760
      },
      {
        "blockId": 165791,
        "x": 1600,
        "y": -660
      },
      {
        "blockId": 165792,
        "x": 2900,
        "y": 840
      },
      {
        "blockId": 165793,
        "x": 2200,
        "y": 920
      },
      {
        "blockId": 165794,
        "x": 1840,
        "y": 920
      },
      {
        "blockId": 165795,
        "x": 1840,
        "y": 1040
      },
      {
        "blockId": 165796,
        "x": 1820,
        "y": 660
      },
      {
        "blockId": 165798,
        "x": 1700,
        "y": 700
      },
      {
        "blockId": 165799,
        "x": 680,
        "y": 660
      },
      {
        "blockId": 165800,
        "x": 400,
        "y": 700
      },
      {
        "blockId": 165801,
        "x": 420,
        "y": 760
      },
      {
        "blockId": 165802,
        "x": 3280,
        "y": 960
      },
      {
        "blockId": 165803,
        "x": 2760,
        "y": 2260
      },
      {
        "blockId": 165804,
        "x": 2500,
        "y": 2100
      },
      {
        "blockId": 165806,
        "x": 2260,
        "y": 2100
      },
      {
        "blockId": 165807,
        "x": 2460,
        "y": 2360
      },
      {
        "blockId": 165808,
        "x": 1460,
        "y": 1900
      },
      {
        "blockId": 165809,
        "x": 400,
        "y": 1300
      },
      {
        "blockId": 165810,
        "x": 1020,
        "y": 2040
      },
      {
        "blockId": 165811,
        "x": 580,
        "y": 2240
      },
      {
        "blockId": 165812,
        "x": 160,
        "y": 2240
      },
      {
        "blockId": 165814,
        "x": -60,
        "y": 2300
      },
      {
        "blockId": 165815,
        "x": -360,
        "y": 2200
      },
      {
        "blockId": 165816,
        "x": -680,
        "y": 2180
      },
      {
        "blockId": 165817,
        "x": -940,
        "y": 2160
      },
      {
        "blockId": 165818,
        "x": -1220,
        "y": 2160
      },
      {
        "blockId": 165819,
        "x": -1480,
        "y": 2160
      },
      {
        "blockId": 165820,
        "x": -1900,
        "y": 2160
      },
      {
        "blockId": 165821,
        "x": -1900,
        "y": 2280
      },
      {
        "blockId": 165822,
        "x": -1480,
        "y": 2280
      },
      {
        "blockId": 165823,
        "x": -700,
        "y": 2460
      },
      {
        "blockId": 165824,
        "x": 120,
        "y": 2560
      },
      {
        "blockId": 165825,
        "x": 580,
        "y": 1940
      },
      {
        "blockId": 165826,
        "x": 580,
        "y": 2040
      },
      {
        "blockId": 165827,
        "x": 280,
        "y": 2040
      },
      {
        "blockId": 165828,
        "x": 280,
        "y": 2140
      },
      {
        "blockId": 165829,
        "x": 1900,
        "y": -460
      },
      {
        "blockId": 165830,
        "x": 1600,
        "y": -480
      },
      {
        "blockId": 165831,
        "x": 1600,
        "y": -380
      },
      {
        "blockId": 165832,
        "x": 1600,
        "y": -180
      },
      {
        "blockId": 165833,
        "x": 1280,
        "y": -320
      },
      {
        "blockId": 165834,
        "x": 1020,
        "y": -320
      },
      {
        "blockId": 165835,
        "x": 640,
        "y": -340
      },
      {
        "blockId": 165837,
        "x": 400,
        "y": 1000
      },
      {
        "blockId": 165838,
        "x": 400,
        "y": 940
      },
      {
        "blockId": 165839,
        "x": 400,
        "y": 1200
      },
      {
        "blockId": 165840,
        "x": 400,
        "y": 1100
      },
      {
        "blockId": 165841,
        "x": 400,
        "y": 1040
      },
      {
        "blockId": 165842,
        "x": 400,
        "y": 1140
      },
      {
        "blockId": 165843,
        "x": 1020,
        "y": -240
      },
      {
        "blockId": 165844,
        "x": 1600,
        "y": -280
      },
      {
        "blockId": 165845,
        "x": 4580,
        "y": 1620
      },
      {
        "blockId": 165846,
        "x": 4280,
        "y": 1640
      },
      {
        "blockId": 165847,
        "x": 3920,
        "y": 1500
      },
      {
        "blockId": 165849,
        "x": 3900,
        "y": 1820
      },
      {
        "blockId": 165850,
        "x": 4340,
        "y": 1900
      },
      {
        "blockId": 165851,
        "x": 3980,
        "y": 2040
      }
    ],
    "frames": [
      {
        "x": -2220,
        "y": 640,
        "width": 1402.08,
        "height": 700,
        "color": [
          0.2823529411764706,
          0.2823529411764706,
          0.2823529411764706
        ],
        "name": "Frame",
        "isCollapsed": false,
        "blocks": [
          165759,
          165760,
          165763,
          165758,
          165761,
          165762,
          165768,
          165772,
          165769,
          165771,
          165775,
          165776,
          165789
        ]
      },
      {
        "x": -1980,
        "y": 1740,
        "width": 3937.13,
        "height": 940,
        "color": [
          0.9372549019607843,
          0.1450980392156863,
          0.1450980392156863
        ],
        "name": "Frame",
        "isCollapsed": false,
        "blocks": [
          165808,
          165810,
          165811,
          165825,
          165826,
          165812,
          165824,
          165814,
          165815,
          165823,
          165816,
          165817,
          165818,
          165819,
          165822,
          165820,
          165821,
          165827,
          165828
        ]
      },
      {
        "x": -330.402,
        "y": 100,
        "width": 1148.44,
        "height": 560,
        "color": [
          0.2823529411764706,
          0.2823529411764706,
          0.2823529411764706
        ],
        "name": "Frame",
        "isCollapsed": false,
        "blocks": [
          165774,
          165777,
          165778,
          165782,
          165780,
          165781
        ]
      },
      {
        "x": 2200,
        "y": 2020,
        "width": 1083.82,
        "height": 460,
        "color": [
          0.2823529411764706,
          0.2823529411764706,
          0.2823529411764706
        ],
        "name": "Frame",
        "isCollapsed": false,
        "blocks": [
          165803,
          165804,
          165807,
          165806
        ]
      },
      {
        "x": 3820,
        "y": 1400,
        "width": 1254.45,
        "height": 960,
        "color": [
          0.2823529411764706,
          0.2823529411764706,
          0.2823529411764706
        ],
        "name": "Frame",
        "isCollapsed": false,
        "blocks": [
          165845,
          165846,
          165847,
          165850,
          165849,
          165851
        ]
      },
      {
        "x": 1500,
        "y": -1080,
        "width": 1158.41,
        "height": 540,
        "color": [
          0.2823529411764706,
          0.2823529411764706,
          0.2823529411764706
        ],
        "name": "BaseColor",
        "isCollapsed": false,
        "blocks": [
          165783,
          165784,
          165785,
          165786,
          165790,
          165791
        ]
      },
      {
        "x": 460,
        "y": -500,
        "width": 1900.56,
        "height": 580,
        "color": [
          0.2823529411764706,
          0.2823529411764706,
          0.2823529411764706
        ],
        "name": "ClearCOat",
        "isCollapsed": false,
        "blocks": [
          165829,
          165830,
          165831,
          165832,
          165833,
          165844,
          165834,
          165835,
          165843
        ]
      }
    ],
    "x": -1135.3474622720084,
    "y": -869.4923556657311,
    "zoom": 0.6852845871174944
  },
  "customType": "BABYLON.NodeMaterial",
  "outputNodes": [
    165758,
    165764
  ],
  "blocks": [
    {
      "customType": "BABYLON.VertexOutputBlock",
      "id": 165758,
      "name": "VertexOutput",
      "comments": "",
      "visibleInInspector": false,
      "visibleOnFrame": false,
      "target": 1,
      "inputs": [
        {
          "name": "vector",
          "inputName": "vector",
          "targetBlockId": 165759,
          "targetConnectionName": "output",
          "isExposedOnFrame": true,
          "exposedPortPosition": -1
        }
      ],
      "outputs": []
    },
    {
      "customType": "BABYLON.TransformBlock",
      "id": 165759,
      "name": "WorldPos * ViewProjectionTransform",
      "comments": "",
      "visibleInInspector": false,
      "visibleOnFrame": false,
      "target": 1,
      "inputs": [
        {
          "name": "vector",
          "inputName": "vector",
          "targetBlockId": 165760,
          "targetConnectionName": "output",
          "isExposedOnFrame": true,
          "exposedPortPosition": -1
        },
        {
          "name": "transform",
          "inputName": "transform",
          "targetBlockId": 165763,
          "targetConnectionName": "output",
          "isExposedOnFrame": true,
          "exposedPortPosition": -1
        }
      ],
      "outputs": [
        {
          "name": "output"
        },
        {
          "name": "xyz"
        }
      ],
      "complementZ": 0,
      "complementW": 1
    },
    {
      "customType": "BABYLON.TransformBlock",
      "id": 165760,
      "name": "WorldPos",
      "comments": "",
      "visibleInInspector": false,
      "visibleOnFrame": false,
      "target": 1,
      "inputs": [
        {
          "name": "vector",
          "inputName": "vector",
          "targetBlockId": 165761,
          "targetConnectionName": "output",
          "isExposedOnFrame": true,
          "exposedPortPosition": -1
        },
        {
          "name": "transform",
          "inputName": "transform",
          "targetBlockId": 165762,
          "targetConnectionName": "output",
          "isExposedOnFrame": true,
          "exposedPortPosition": -1
        }
      ],
      "outputs": [
        {
          "name": "output"
        },
        {
          "name": "xyz"
        }
      ],
      "complementZ": 0,
      "complementW": 1
    },
    {
      "customType": "BABYLON.InputBlock",
      "id": 165761,
      "name": "position",
      "comments": "",
      "visibleInInspector": false,
      "visibleOnFrame": false,
      "target": 1,
      "inputs": [],
      "outputs": [
        {
          "name": "output"
        }
      ],
      "type": 8,
      "mode": 1,
      "animationType": 0,
      "min": 0,
      "max": 0,
      "isBoolean": false,
      "matrixMode": 0,
      "isConstant": false,
      "groupInInspector": "",
      "convertToGammaSpace": false,
      "convertToLinearSpace": false
    },
    {
      "customType": "BABYLON.InputBlock",
      "id": 165762,
      "name": "World",
      "comments": "",
      "visibleInInspector": false,
      "visibleOnFrame": false,
      "target": 1,
      "inputs": [],
      "outputs": [
        {
          "name": "output"
        }
      ],
      "type": 128,
      "mode": 0,
      "systemValue": 1,
      "animationType": 0,
      "min": 0,
      "max": 0,
      "isBoolean": false,
      "matrixMode": 0,
      "isConstant": false,
      "groupInInspector": "",
      "convertToGammaSpace": false,
      "convertToLinearSpace": false
    },
    {
      "customType": "BABYLON.InputBlock",
      "id": 165763,
      "name": "ViewProjection",
      "comments": "",
      "visibleInInspector": false,
      "visibleOnFrame": false,
      "target": 1,
      "inputs": [],
      "outputs": [
        {
          "name": "output"
        }
      ],
      "type": 128,
      "mode": 0,
      "systemValue": 4,
      "animationType": 0,
      "min": 0,
      "max": 0,
      "isBoolean": false,
      "matrixMode": 0,
      "isConstant": false,
      "groupInInspector": "",
      "convertToGammaSpace": false,
      "convertToLinearSpace": false
    },
    {
      "customType": "BABYLON.FragmentOutputBlock",
      "id": 165764,
      "name": "FragmentOutput",
      "comments": "",
      "visibleInInspector": false,
      "visibleOnFrame": false,
      "target": 2,
      "inputs": [
        {
          "name": "rgba",
          "isExposedOnFrame": true,
          "exposedPortPosition": -1
        },
        {
          "name": "rgb",
          "inputName": "rgb",
          "targetBlockId": 165765,
          "targetConnectionName": "output",
          "isExposedOnFrame": true,
          "exposedPortPosition": -1
        },
        {
          "name": "a"
        }
      ],
      "outputs": [],
      "useLogarithmicDepth": false
    },
    {
      "customType": "BABYLON.ElbowBlock",
      "id": 165765,
      "name": "",
      "comments": "",
      "visibleInInspector": false,
      "visibleOnFrame": false,
      "target": 4,
      "inputs": [
        {
          "name": "input",
          "inputName": "input",
          "targetBlockId": 165766,
          "targetConnectionName": "output",
          "isExposedOnFrame": true,
          "exposedPortPosition": -1
        }
      ],
      "outputs": [
        {
          "name": "output"
        }
      ]
    },
    {
      "customType": "BABYLON.AddBlock",
      "id": 165766,
      "name": "Add",
      "comments": "",
      "visibleInInspector": false,
      "visibleOnFrame": false,
      "target": 4,
      "inputs": [
        {
          "name": "left",
          "displayName": "left",
          "inputName": "left",
          "targetBlockId": 165767,
          "targetConnectionName": "lighting",
          "isExposedOnFrame": true,
          "exposedPortPosition": 5
        },
        {
          "name": "right",
          "displayName": "right",
          "inputName": "right",
          "targetBlockId": 165845,
          "targetConnectionName": "output",
          "isExposedOnFrame": true,
          "exposedPortPosition": -1
        }
      ],
      "outputs": [
        {
          "name": "output",
          "displayName": "output"
        }
      ]
    },
    {
      "customType": "BABYLON.PBRMetallicRoughnessBlock",
      "id": 165767,
      "name": "PBRMetallicRoughness",
      "comments": "",
      "visibleInInspector": false,
      "visibleOnFrame": false,
      "target": 3,
      "inputs": [
        {
          "name": "worldPosition",
          "inputName": "worldPosition",
          "targetBlockId": 165760,
          "targetConnectionName": "output",
          "isExposedOnFrame": true,
          "exposedPortPosition": -1
        },
        {
          "name": "worldNormal",
          "inputName": "worldNormal",
          "targetBlockId": 165768,
          "targetConnectionName": "output",
          "isExposedOnFrame": true,
          "exposedPortPosition": -1
        },
        {
          "name": "view",
          "inputName": "view",
          "targetBlockId": 165770,
          "targetConnectionName": "output",
          "isExposedOnFrame": true,
          "exposedPortPosition": -1
        },
        {
          "name": "cameraPosition",
          "inputName": "cameraPosition",
          "targetBlockId": 165772,
          "targetConnectionName": "output",
          "isExposedOnFrame": true,
          "exposedPortPosition": -1
        },
        {
          "name": "perturbedNormal",
          "inputName": "perturbedNormal",
          "targetBlockId": 165773,
          "targetConnectionName": "output",
          "isExposedOnFrame": true,
          "exposedPortPosition": -1
        },
        {
          "name": "baseColor",
          "inputName": "baseColor",
          "targetBlockId": 165783,
          "targetConnectionName": "output",
          "isExposedOnFrame": true,
          "exposedPortPosition": -1
        },
        {
          "name": "metallic",
          "inputName": "metallic",
          "targetBlockId": 165792,
          "targetConnectionName": "output",
          "isExposedOnFrame": true,
          "exposedPortPosition": -1
        },
        {
          "name": "roughness",
          "inputName": "roughness",
          "targetBlockId": 165793,
          "targetConnectionName": "output",
          "isExposedOnFrame": true,
          "exposedPortPosition": -1
        },
        {
          "name": "ambientOcc",
          "inputName": "ambientOcc",
          "targetBlockId": 165802,
          "targetConnectionName": "output",
          "isExposedOnFrame": true,
          "exposedPortPosition": -1
        },
        {
          "name": "opacity"
        },
        {
          "name": "indexOfRefraction"
        },
        {
          "name": "ambientColor"
        },
        {
          "name": "reflection",
          "inputName": "reflection",
          "targetBlockId": 165808,
          "targetConnectionName": "reflection",
          "isExposedOnFrame": true,
          "exposedPortPosition": -1
        },
        {
          "name": "clearcoat",
          "inputName": "clearcoat",
          "targetBlockId": 165829,
          "targetConnectionName": "clearcoat",
          "isExposedOnFrame": true,
          "exposedPortPosition": -1
        },
        {
          "name": "sheen",
          "isExposedOnFrame": true,
          "exposedPortPosition": -1
        },
        {
          "name": "subsurface"
        },
        {
          "name": "anisotropy"
        },
        {
          "name": "iridescence"
        }
      ],
      "outputs": [
        {
          "name": "ambientClr"
        },
        {
          "name": "diffuseDir"
        },
        {
          "name": "specularDir"
        },
        {
          "name": "clearcoatDir"
        },
        {
          "name": "sheenDir"
        },
        {
          "name": "diffuseInd"
        },
        {
          "name": "specularInd"
        },
        {
          "name": "clearcoatInd"
        },
        {
          "name": "sheenInd"
        },
        {
          "name": "refraction"
        },
        {
          "name": "lighting"
        },
        {
          "name": "shadow"
        },
        {
          "name": "alpha"
        }
      ],
      "enableToneMapping": true,
      "toneMappingType": 1,
      "lightFalloff": 0,
      "directIntensity": 1,
      "environmentIntensity": 1,
      "specularIntensity": 1,
      "useAlphaTest": false,
      "alphaTestCutoff": 0.75,
      "useAlphaBlending": false,
      "useRadianceOverAlpha": true,
      "useSpecularOverAlpha": true,
      "enableSpecularAntiAliasing": false,
      "realTimeFiltering": false,
      "realTimeFilteringQuality": 8,
      "useEnergyConservation": true,
      "useRadianceOcclusion": true,
      "useHorizonOcclusion": true,
      "unlit": false,
      "forceNormalForward": false,
      "debugMode": 0,
      "debugLimit": 0,
      "debugFactor": 1
    },
    {
      "customType": "BABYLON.TransformBlock",
      "id": 165768,
      "name": "World normal",
      "comments": "",
      "visibleInInspector": false,
      "visibleOnFrame": false,
      "target": 1,
      "inputs": [
        {
          "name": "vector",
          "inputName": "vector",
          "targetBlockId": 165769,
          "targetConnectionName": "output",
          "isExposedOnFrame": true,
          "exposedPortPosition": -1
        },
        {
          "name": "transform",
          "inputName": "transform",
          "targetBlockId": 165762,
          "targetConnectionName": "output",
          "isExposedOnFrame": true,
          "exposedPortPosition": -1
        }
      ],
      "outputs": [
        {
          "name": "output"
        },
        {
          "name": "xyz"
        }
      ],
      "complementZ": 0,
      "complementW": 0
    },
    {
      "customType": "BABYLON.InputBlock",
      "id": 165769,
      "name": "normal",
      "comments": "",
      "visibleInInspector": false,
      "visibleOnFrame": false,
      "target": 1,
      "inputs": [],
      "outputs": [
        {
          "name": "output"
        }
      ],
      "type": 8,
      "mode": 1,
      "animationType": 0,
      "min": 0,
      "max": 0,
      "isBoolean": false,
      "matrixMode": 0,
      "isConstant": false,
      "groupInInspector": "",
      "convertToGammaSpace": false,
      "convertToLinearSpace": false
    },
    {
      "customType": "BABYLON.ElbowBlock",
      "id": 165770,
      "name": "VIEW",
      "comments": "",
      "visibleInInspector": false,
      "visibleOnFrame": false,
      "target": 1,
      "inputs": [
        {
          "name": "input",
          "inputName": "input",
          "targetBlockId": 165771,
          "targetConnectionName": "output",
          "isExposedOnFrame": true,
          "exposedPortPosition": -1
        }
      ],
      "outputs": [
        {
          "name": "output"
        }
      ]
    },
    {
      "customType": "BABYLON.InputBlock",
      "id": 165771,
      "name": "view",
      "comments": "",
      "visibleInInspector": false,
      "visibleOnFrame": false,
      "target": 1,
      "inputs": [],
      "outputs": [
        {
          "name": "output"
        }
      ],
      "type": 128,
      "mode": 0,
      "systemValue": 2,
      "animationType": 0,
      "min": 0,
      "max": 0,
      "isBoolean": false,
      "matrixMode": 0,
      "isConstant": false,
      "groupInInspector": "",
      "convertToGammaSpace": false,
      "convertToLinearSpace": false
    },
    {
      "customType": "BABYLON.InputBlock",
      "id": 165772,
      "name": "cameraPosition",
      "comments": "",
      "visibleInInspector": false,
      "visibleOnFrame": false,
      "target": 1,
      "inputs": [],
      "outputs": [
        {
          "name": "output"
        }
      ],
      "type": 8,
      "mode": 0,
      "systemValue": 7,
      "animationType": 0,
      "min": 0,
      "max": 0,
      "isBoolean": false,
      "matrixMode": 0,
      "isConstant": false,
      "groupInInspector": "",
      "convertToGammaSpace": false,
      "convertToLinearSpace": false
    },
    {
      "customType": "BABYLON.ElbowBlock",
      "id": 165773,
      "name": "",
      "comments": "",
      "visibleInInspector": false,
      "visibleOnFrame": false,
      "target": 2,
      "inputs": [
        {
          "name": "input",
          "inputName": "input",
          "targetBlockId": 165774,
          "targetConnectionName": "output",
          "isExposedOnFrame": true,
          "exposedPortPosition": -1
        }
      ],
      "outputs": [
        {
          "name": "output"
        }
      ]
    },
    {
      "customType": "BABYLON.PerturbNormalBlock",
      "id": 165774,
      "name": "Perturb normal",
      "comments": "",
      "visibleInInspector": false,
      "visibleOnFrame": false,
      "target": 2,
      "inputs": [
        {
          "name": "worldPosition",
          "inputName": "worldPosition",
          "targetBlockId": 165760,
          "targetConnectionName": "output",
          "isExposedOnFrame": true,
          "exposedPortPosition": -1
        },
        {
          "name": "worldNormal",
          "inputName": "worldNormal",
          "targetBlockId": 165768,
          "targetConnectionName": "output",
          "isExposedOnFrame": true,
          "exposedPortPosition": -1
        },
        {
          "name": "worldTangent",
          "inputName": "worldTangent",
          "targetBlockId": 165775,
          "targetConnectionName": "output",
          "isExposedOnFrame": true,
          "exposedPortPosition": -1
        },
        {
          "name": "uv",
          "inputName": "uv",
          "targetBlockId": 165777,
          "targetConnectionName": "output",
          "isExposedOnFrame": true,
          "exposedPortPosition": -1
        },
        {
          "name": "normalMapColor",
          "inputName": "normalMapColor",
          "targetBlockId": 165778,
          "targetConnectionName": "rgb",
          "isExposedOnFrame": true,
          "exposedPortPosition": -1
        },
        {
          "name": "strength",
          "inputName": "strength",
          "targetBlockId": 165782,
          "targetConnectionName": "output",
          "isExposedOnFrame": true,
          "exposedPortPosition": -1
        },
        {
          "name": "viewDirection"
        },
        {
          "name": "parallaxScale"
        },
        {
          "name": "parallaxHeight"
        },
        {
          "name": "TBN"
        }
      ],
      "outputs": [
        {
          "name": "output"
        },
        {
          "name": "uvOffset"
        }
      ],
      "invertX": false,
      "invertY": false,
      "useParallaxOcclusion": false
    },
    {
      "customType": "BABYLON.TransformBlock",
      "id": 165775,
      "name": "World tangent",
      "comments": "",
      "visibleInInspector": false,
      "visibleOnFrame": false,
      "target": 1,
      "inputs": [
        {
          "name": "vector",
          "inputName": "vector",
          "targetBlockId": 165776,
          "targetConnectionName": "output",
          "isExposedOnFrame": true,
          "exposedPortPosition": -1
        },
        {
          "name": "transform",
          "inputName": "transform",
          "targetBlockId": 165762,
          "targetConnectionName": "output",
          "isExposedOnFrame": true,
          "exposedPortPosition": -1
        }
      ],
      "outputs": [
        {
          "name": "output"
        },
        {
          "name": "xyz"
        }
      ],
      "complementZ": 0,
      "complementW": 0
    },
    {
      "customType": "BABYLON.InputBlock",
      "id": 165776,
      "name": "tangent",
      "comments": "",
      "visibleInInspector": false,
      "visibleOnFrame": false,
      "target": 1,
      "inputs": [],
      "outputs": [
        {
          "name": "output"
        }
      ],
      "type": 16,
      "mode": 1,
      "animationType": 0,
      "min": 0,
      "max": 0,
      "isBoolean": false,
      "matrixMode": 0,
      "isConstant": false,
      "groupInInspector": "",
      "convertToGammaSpace": false,
      "convertToLinearSpace": false
    },
    {
      "customType": "BABYLON.InputBlock",
      "id": 165777,
      "name": "uv",
      "comments": "",
      "visibleInInspector": false,
      "visibleOnFrame": false,
      "target": 1,
      "inputs": [],
      "outputs": [
        {
          "name": "output"
        }
      ],
      "type": 4,
      "mode": 1,
      "animationType": 0,
      "min": 0,
      "max": 0,
      "isBoolean": false,
      "matrixMode": 0,
      "isConstant": false,
      "groupInInspector": "",
      "convertToGammaSpace": false,
      "convertToLinearSpace": false
    },
    {
      "customType": "BABYLON.TextureBlock",
      "id": 165778,
      "name": "normalTex",
      "comments": "",
      "visibleInInspector": false,
      "visibleOnFrame": false,
      "target": 3,
      "inputs": [
        {
          "name": "uv",
          "inputName": "uv",
          "targetBlockId": 165780,
          "targetConnectionName": "output",
          "isExposedOnFrame": true,
          "exposedPortPosition": -1
        },
        {
          "name": "source"
        }
      ],
      "outputs": [
        {
          "name": "rgba"
        },
        {
          "name": "rgb"
        },
        {
          "name": "r"
        },
        {
          "name": "g"
        },
        {
          "name": "b"
        },
        {
          "name": "a"
        },
        {
          "name": "level"
        }
      ],
      "convertToGammaSpace": false,
      "convertToLinearSpace": false,
      "fragmentOnly": false,
      "disableLevelMultiplication": false,
      "texture": {
        "tags": null,
        "url": "",
        "uOffset": 0,
        "vOffset": 0,
        "uScale": 1,
        "vScale": 1,
        "uAng": 0,
        "vAng": 0,
        "wAng": 0,
        "uRotationCenter": 0.5,
        "vRotationCenter": 0.5,
        "wRotationCenter": 0.5,
        "homogeneousRotationInUVTransform": false,
        "isBlocking": true,
        "name": "data:image/png,iVBORw0KGgoAAAANSUhE_1901599054",
        "hasAlpha": false,
        "getAlphaFromRGB": false,
        "level": 1,
        "coordinatesIndex": 0,
        "optimizeUVAllocation": true,
        "coordinatesMode": 7,
        "wrapU": 1,
        "wrapV": 1,
        "wrapR": 1,
        "anisotropicFilteringLevel": 4,
        "isCube": false,
        "is3D": false,
        "is2DArray": false,
        "gammaSpace": true,
        "invertZ": false,
        "lodLevelInAlpha": false,
        "lodGenerationOffset": 0,
        "lodGenerationScale": 0,
        "linearSpecularLOD": false,
        "isRenderTarget": false,
        "animations": [],
        "invertY": false,
        "samplingMode": 3,
        "_useSRGBBuffer": false
      }
    },
    {
      "customType": "BABYLON.ScaleBlock",
      "id": 165780,
      "name": "Scale",
      "comments": "",
      "visibleInInspector": false,
      "visibleOnFrame": false,
      "target": 4,
      "inputs": [
        {
          "name": "input",
          "inputName": "input",
          "targetBlockId": 165777,
          "targetConnectionName": "output",
          "isExposedOnFrame": true,
          "exposedPortPosition": -1
        },
        {
          "name": "factor",
          "inputName": "factor",
          "targetBlockId": 165781,
          "targetConnectionName": "output",
          "isExposedOnFrame": true,
          "exposedPortPosition": -1
        }
      ],
      "outputs": [
        {
          "name": "output"
        }
      ]
    },
    {
      "customType": "BABYLON.InputBlock",
      "id": 165781,
      "name": "Float",
      "comments": "",
      "visibleInInspector": false,
      "visibleOnFrame": false,
      "target": 1,
      "inputs": [],
      "outputs": [
        {
          "name": "output"
        }
      ],
      "type": 1,
      "mode": 0,
      "animationType": 0,
      "min": 0,
      "max": 85,
      "isBoolean": false,
      "matrixMode": 0,
      "isConstant": false,
      "groupInInspector": "",
      "convertToGammaSpace": false,
      "convertToLinearSpace": false,
      "valueType": "number",
      "value": 65
    },
    {
      "customType": "BABYLON.InputBlock",
      "id": 165782,
      "name": "strength",
      "comments": "",
      "visibleInInspector": false,
      "visibleOnFrame": false,
      "target": 1,
      "inputs": [],
      "outputs": [
        {
          "name": "output"
        }
      ],
      "type": 1,
      "mode": 0,
      "animationType": 0,
      "min": 0,
      "max": 0.5,
      "isBoolean": false,
      "matrixMode": 0,
      "isConstant": false,
      "groupInInspector": "",
      "convertToGammaSpace": false,
      "convertToLinearSpace": false,
      "valueType": "number",
      "value": 0.2
    },
    {
      "customType": "BABYLON.LerpBlock",
      "id": 165783,
      "name": "Lerp",
      "comments": "",
      "visibleInInspector": false,
      "visibleOnFrame": false,
      "target": 4,
      "inputs": [
        {
          "name": "left",
          "inputName": "left",
          "targetBlockId": 165784,
          "targetConnectionName": "output",
          "isExposedOnFrame": true,
          "exposedPortPosition": -1
        },
        {
          "name": "right",
          "inputName": "right",
          "targetBlockId": 165785,
          "targetConnectionName": "output",
          "isExposedOnFrame": true,
          "exposedPortPosition": -1
        },
        {
          "name": "gradient",
          "inputName": "gradient",
          "targetBlockId": 165786,
          "targetConnectionName": "fresnel",
          "isExposedOnFrame": true,
          "exposedPortPosition": -1
        }
      ],
      "outputs": [
        {
          "name": "output"
        }
      ]
    },
    {
      "customType": "BABYLON.InputBlock",
      "id": 165784,
      "name": "baseColor_Edge",
      "comments": "",
      "visibleInInspector": true,
      "visibleOnFrame": false,
      "target": 1,
      "inputs": [],
      "outputs": [
        {
          "name": "output"
        }
      ],
      "type": 32,
      "mode": 0,
      "animationType": 0,
      "min": 0,
      "max": 0,
      "isBoolean": false,
      "matrixMode": 0,
      "isConstant": false,
      "groupInInspector": "",
      "convertToGammaSpace": false,
      "convertToLinearSpace": false,
      "valueType": "BABYLON.Color3",
      "value": [
        1,
        1,
        1
      ]
    },
    {
      "customType": "BABYLON.InputBlock",
      "id": 165785,
      "name": "baseColor_Center",
      "comments": "",
      "visibleInInspector": true,
      "visibleOnFrame": false,
      "target": 1,
      "inputs": [],
      "outputs": [
        {
          "name": "output"
        }
      ],
      "type": 32,
      "mode": 0,
      "animationType": 0,
      "min": 0,
      "max": 0,
      "isBoolean": false,
      "matrixMode": 0,
      "isConstant": false,
      "groupInInspector": "",
      "convertToGammaSpace": false,
      "convertToLinearSpace": false,
      "valueType": "BABYLON.Color3",
      "value": [
        0.5176470588235295,
        0.5529411764705883,
        0.5725490196078431
      ]
    },
    {
      "customType": "BABYLON.FresnelBlock",
      "id": 165786,
      "name": "Fresnel",
      "comments": "",
      "visibleInInspector": false,
      "visibleOnFrame": false,
      "target": 4,
      "inputs": [
        {
          "name": "worldNormal",
          "displayName": "worldNormal",
          "inputName": "worldNormal",
          "targetBlockId": 165787,
          "targetConnectionName": "output",
          "isExposedOnFrame": true,
          "exposedPortPosition": 0
        },
        {
          "name": "viewDirection",
          "displayName": "viewDirection",
          "inputName": "viewDirection",
          "targetBlockId": 165788,
          "targetConnectionName": "output",
          "isExposedOnFrame": true,
          "exposedPortPosition": 1
        },
        {
          "name": "bias",
          "displayName": "bias",
          "inputName": "bias",
          "targetBlockId": 165790,
          "targetConnectionName": "output",
          "isExposedOnFrame": true,
          "exposedPortPosition": -1
        },
        {
          "name": "power",
          "displayName": "power",
          "inputName": "power",
          "targetBlockId": 165791,
          "targetConnectionName": "output",
          "isExposedOnFrame": true,
          "exposedPortPosition": -1
        }
      ],
      "outputs": [
        {
          "name": "fresnel",
          "displayName": "fresnel"
        }
      ]
    },
    {
      "customType": "BABYLON.ElbowBlock",
      "id": 165787,
      "name": "",
      "comments": "",
      "visibleInInspector": false,
      "visibleOnFrame": false,
      "target": 1,
      "inputs": [
        {
          "name": "input",
          "inputName": "input",
          "targetBlockId": 165768,
          "targetConnectionName": "output",
          "isExposedOnFrame": true,
          "exposedPortPosition": -1
        }
      ],
      "outputs": [
        {
          "name": "output"
        }
      ]
    },
    {
      "customType": "BABYLON.ElbowBlock",
      "id": 165788,
      "name": "",
      "comments": "",
      "visibleInInspector": false,
      "visibleOnFrame": false,
      "target": 4,
      "inputs": [
        {
          "name": "input",
          "inputName": "input",
          "targetBlockId": 165789,
          "targetConnectionName": "output",
          "isExposedOnFrame": true,
          "exposedPortPosition": -1
        }
      ],
      "outputs": [
        {
          "name": "output"
        }
      ]
    },
    {
      "customType": "BABYLON.ViewDirectionBlock",
      "id": 165789,
      "name": "View direction",
      "comments": "",
      "visibleInInspector": false,
      "visibleOnFrame": false,
      "target": 4,
      "inputs": [
        {
          "name": "worldPosition",
          "inputName": "worldPosition",
          "targetBlockId": 165760,
          "targetConnectionName": "output",
          "isExposedOnFrame": true,
          "exposedPortPosition": -1
        },
        {
          "name": "cameraPosition",
          "inputName": "cameraPosition",
          "targetBlockId": 165772,
          "targetConnectionName": "output",
          "isExposedOnFrame": true,
          "exposedPortPosition": -1
        }
      ],
      "outputs": [
        {
          "name": "output"
        }
      ]
    },
    {
      "customType": "BABYLON.InputBlock",
      "id": 165790,
      "name": "bias",
      "comments": "",
      "visibleInInspector": false,
      "visibleOnFrame": false,
      "target": 1,
      "inputs": [],
      "outputs": [
        {
          "name": "output"
        }
      ],
      "type": 1,
      "mode": 0,
      "animationType": 0,
      "min": 0,
      "max": 1,
      "isBoolean": false,
      "matrixMode": 0,
      "isConstant": false,
      "groupInInspector": "",
      "convertToGammaSpace": false,
      "convertToLinearSpace": false,
      "valueType": "number",
      "value": 0.7
    },
    {
      "customType": "BABYLON.InputBlock",
      "id": 165791,
      "name": "power",
      "comments": "",
      "visibleInInspector": false,
      "visibleOnFrame": false,
      "target": 1,
      "inputs": [],
      "outputs": [
        {
          "name": "output"
        }
      ],
      "type": 1,
      "mode": 0,
      "animationType": 0,
      "min": 0,
      "max": 20,
      "isBoolean": false,
      "matrixMode": 0,
      "isConstant": false,
      "groupInInspector": "",
      "convertToGammaSpace": false,
      "convertToLinearSpace": false,
      "valueType": "number",
      "value": 5
    },
    {
      "customType": "BABYLON.InputBlock",
      "id": 165792,
      "name": "metallic",
      "comments": "",
      "visibleInInspector": true,
      "visibleOnFrame": false,
      "target": 1,
      "inputs": [],
      "outputs": [
        {
          "name": "output"
        }
      ],
      "type": 1,
      "mode": 0,
      "animationType": 0,
      "min": 0,
      "max": 1,
      "isBoolean": false,
      "matrixMode": 0,
      "isConstant": false,
      "groupInInspector": "",
      "convertToGammaSpace": false,
      "convertToLinearSpace": false,
      "valueType": "number",
      "value": 1
    },
    {
      "customType": "BABYLON.LerpBlock",
      "id": 165793,
      "name": "Lerp",
      "comments": "",
      "visibleInInspector": false,
      "visibleOnFrame": false,
      "target": 4,
      "inputs": [
        {
          "name": "left",
          "inputName": "left",
          "targetBlockId": 165794,
          "targetConnectionName": "output",
          "isExposedOnFrame": true,
          "exposedPortPosition": -1
        },
        {
          "name": "right",
          "inputName": "right",
          "targetBlockId": 165795,
          "targetConnectionName": "output",
          "isExposedOnFrame": true,
          "exposedPortPosition": -1
        },
        {
          "name": "gradient",
          "inputName": "gradient",
          "targetBlockId": 165796,
          "targetConnectionName": "r",
          "isExposedOnFrame": true,
          "exposedPortPosition": -1
        }
      ],
      "outputs": [
        {
          "name": "output"
        }
      ]
    },
    {
      "customType": "BABYLON.InputBlock",
      "id": 165794,
      "name": "roughness",
      "comments": "",
      "visibleInInspector": true,
      "visibleOnFrame": false,
      "target": 1,
      "inputs": [],
      "outputs": [
        {
          "name": "output"
        }
      ],
      "type": 1,
      "mode": 0,
      "animationType": 0,
      "min": 0,
      "max": 1,
      "isBoolean": false,
      "matrixMode": 0,
      "isConstant": false,
      "groupInInspector": "",
      "convertToGammaSpace": false,
      "convertToLinearSpace": false,
      "valueType": "number",
      "value": 0.55
    },
    {
      "customType": "BABYLON.InputBlock",
      "id": 165795,
      "name": "roughness",
      "comments": "",
      "visibleInInspector": true,
      "visibleOnFrame": false,
      "target": 1,
      "inputs": [],
      "outputs": [
        {
          "name": "output"
        }
      ],
      "type": 1,
      "mode": 0,
      "animationType": 0,
      "min": 0,
      "max": 1,
      "isBoolean": false,
      "matrixMode": 0,
      "isConstant": false,
      "groupInInspector": "",
      "convertToGammaSpace": false,
      "convertToLinearSpace": false,
      "valueType": "number",
      "value": 0.35
    },
    {
      "customType": "BABYLON.TextureBlock",
      "id": 165796,
      "name": "Texture",
      "comments": "",
      "visibleInInspector": false,
      "visibleOnFrame": false,
      "target": 3,
      "inputs": [
        {
          "name": "uv",
          "inputName": "uv",
          "targetBlockId": 165798,
          "targetConnectionName": "output",
          "isExposedOnFrame": true,
          "exposedPortPosition": -1
        },
        {
          "name": "source"
        }
      ],
      "outputs": [
        {
          "name": "rgba"
        },
        {
          "name": "rgb"
        },
        {
          "name": "r"
        },
        {
          "name": "g"
        },
        {
          "name": "b"
        },
        {
          "name": "a"
        },
        {
          "name": "level"
        }
      ],
      "convertToGammaSpace": false,
      "convertToLinearSpace": false,
      "fragmentOnly": false,
      "disableLevelMultiplication": false,
      "texture": {
        "tags": null,
        "url": "",
        "uOffset": 0,
        "vOffset": 0,
        "uScale": 1,
        "vScale": 1,
        "uAng": 0,
        "vAng": 0,
        "wAng": 0,
        "uRotationCenter": 0.5,
        "vRotationCenter": 0.5,
        "wRotationCenter": 0.5,
        "homogeneousRotationInUVTransform": false,
        "isBlocking": true,
        "name": "data:image/png,iVBORw0KGgoAAAANSUhE_1131255549",
        "hasAlpha": false,
        "getAlphaFromRGB": false,
        "level": 1,
        "coordinatesIndex": 0,
        "optimizeUVAllocation": true,
        "coordinatesMode": 7,
        "wrapU": 1,
        "wrapV": 1,
        "wrapR": 1,
        "anisotropicFilteringLevel": 4,
        "isCube": false,
        "is3D": false,
        "is2DArray": false,
        "gammaSpace": true,
        "invertZ": false,
        "lodLevelInAlpha": false,
        "lodGenerationOffset": 0,
        "lodGenerationScale": 0,
        "linearSpecularLOD": false,
        "isRenderTarget": false,
        "animations": [],
        "invertY": false,
        "samplingMode": 3,
        "_useSRGBBuffer": false
      }
    },
    {
      "customType": "BABYLON.ElbowBlock",
      "id": 165798,
      "name": "",
      "comments": "",
      "visibleInInspector": false,
      "visibleOnFrame": false,
      "target": 4,
      "inputs": [
        {
          "name": "input",
          "inputName": "input",
          "targetBlockId": 165799,
          "targetConnectionName": "output",
          "isExposedOnFrame": true,
          "exposedPortPosition": -1
        }
      ],
      "outputs": [
        {
          "name": "output"
        }
      ]
    },
    {
      "customType": "BABYLON.ScaleBlock",
      "id": 165799,
      "name": "Scale",
      "comments": "",
      "visibleInInspector": false,
      "visibleOnFrame": false,
      "target": 4,
      "inputs": [
        {
          "name": "input",
          "inputName": "input",
          "targetBlockId": 165800,
          "targetConnectionName": "output",
          "isExposedOnFrame": true,
          "exposedPortPosition": -1
        },
        {
          "name": "factor",
          "inputName": "factor",
          "targetBlockId": 165801,
          "targetConnectionName": "output",
          "isExposedOnFrame": true,
          "exposedPortPosition": -1
        }
      ],
      "outputs": [
        {
          "name": "output"
        }
      ]
    },
    {
      "customType": "BABYLON.ElbowBlock",
      "id": 165800,
      "name": "",
      "comments": "",
      "visibleInInspector": false,
      "visibleOnFrame": false,
      "target": 4,
      "inputs": [
        {
          "name": "input",
          "inputName": "input",
          "targetBlockId": 165780,
          "targetConnectionName": "output",
          "isExposedOnFrame": true,
          "exposedPortPosition": -1
        }
      ],
      "outputs": [
        {
          "name": "output"
        }
      ]
    },
    {
      "customType": "BABYLON.InputBlock",
      "id": 165801,
      "name": "Float",
      "comments": "",
      "visibleInInspector": false,
      "visibleOnFrame": false,
      "target": 1,
      "inputs": [],
      "outputs": [
        {
          "name": "output"
        }
      ],
      "type": 1,
      "mode": 0,
      "animationType": 0,
      "min": 0,
      "max": 2,
      "isBoolean": false,
      "matrixMode": 0,
      "isConstant": false,
      "groupInInspector": "",
      "convertToGammaSpace": false,
      "convertToLinearSpace": false,
      "valueType": "number",
      "value": 0.5
    },
    {
      "customType": "BABYLON.ElbowBlock",
      "id": 165802,
      "name": "",
      "comments": "",
      "visibleInInspector": false,
      "visibleOnFrame": false,
      "target": 4,
      "inputs": [
        {
          "name": "input",
          "inputName": "input",
          "targetBlockId": 165803,
          "targetConnectionName": "output",
          "isExposedOnFrame": true,
          "exposedPortPosition": -1
        }
      ],
      "outputs": [
        {
          "name": "output"
        }
      ]
    },
    {
      "customType": "BABYLON.PowBlock",
      "id": 165803,
      "name": "Pow",
      "comments": "",
      "visibleInInspector": false,
      "visibleOnFrame": false,
      "target": 4,
      "inputs": [
        {
          "name": "value",
          "inputName": "value",
          "targetBlockId": 165804,
          "targetConnectionName": "r",
          "isExposedOnFrame": true,
          "exposedPortPosition": -1
        },
        {
          "name": "power",
          "inputName": "power",
          "targetBlockId": 165807,
          "targetConnectionName": "output",
          "isExposedOnFrame": true,
          "exposedPortPosition": -1
        }
      ],
      "outputs": [
        {
          "name": "output"
        }
      ]
    },
    {
      "customType": "BABYLON.TextureBlock",
      "id": 165804,
      "name": "Texture",
      "comments": "",
      "visibleInInspector": false,
      "visibleOnFrame": false,
      "target": 3,
      "inputs": [
        {
          "name": "uv",
          "inputName": "uv",
          "targetBlockId": 165806,
          "targetConnectionName": "output",
          "isExposedOnFrame": true,
          "exposedPortPosition": -1
        },
        {
          "name": "source"
        }
      ],
      "outputs": [
        {
          "name": "rgba"
        },
        {
          "name": "rgb"
        },
        {
          "name": "r"
        },
        {
          "name": "g"
        },
        {
          "name": "b"
        },
        {
          "name": "a"
        },
        {
          "name": "level"
        }
      ],
      "convertToGammaSpace": false,
      "convertToLinearSpace": false,
      "fragmentOnly": false,
      "disableLevelMultiplication": false,
      "texture": {
        "tags": null,
        "url": "",
        "uOffset": 0,
        "vOffset": 0,
        "uScale": 1,
        "vScale": 1,
        "uAng": 0,
        "vAng": 0,
        "wAng": 0,
        "uRotationCenter": 0.5,
        "vRotationCenter": 0.5,
        "wRotationCenter": 0.5,
        "homogeneousRotationInUVTransform": false,
        "isBlocking": true,
        "name": "data:image/png,iVBORw0KGgoAAAANSUhE_-1237614186",
        "hasAlpha": false,
        "getAlphaFromRGB": false,
        "level": 1,
        "coordinatesIndex": 0,
        "optimizeUVAllocation": true,
        "coordinatesMode": 7,
        "wrapU": 1,
        "wrapV": 1,
        "wrapR": 1,
        "anisotropicFilteringLevel": 4,
        "isCube": false,
        "is3D": false,
        "is2DArray": false,
        "gammaSpace": true,
        "invertZ": false,
        "lodLevelInAlpha": false,
        "lodGenerationOffset": 0,
        "lodGenerationScale": 0,
        "linearSpecularLOD": false,
        "isRenderTarget": false,
        "animations": [],
        "invertY": false,
        "samplingMode": 3,
        "_useSRGBBuffer": false
      }
    },
    {
      "customType": "BABYLON.InputBlock",
      "id": 165806,
      "name": "uv",
      "comments": "",
      "visibleInInspector": false,
      "visibleOnFrame": false,
      "target": 1,
      "inputs": [],
      "outputs": [
        {
          "name": "output"
        }
      ],
      "type": 4,
      "mode": 1,
      "animationType": 0,
      "min": 0,
      "max": 0,
      "isBoolean": false,
      "matrixMode": 0,
      "isConstant": false,
      "groupInInspector": "",
      "convertToGammaSpace": false,
      "convertToLinearSpace": false
    },
    {
      "customType": "BABYLON.InputBlock",
      "id": 165807,
      "name": "Float",
      "comments": "",
      "visibleInInspector": false,
      "visibleOnFrame": false,
      "target": 1,
      "inputs": [],
      "outputs": [
        {
          "name": "output"
        }
      ],
      "type": 1,
      "mode": 0,
      "animationType": 0,
      "min": 0.2,
      "max": 1,
      "isBoolean": false,
      "matrixMode": 0,
      "isConstant": false,
      "groupInInspector": "",
      "convertToGammaSpace": false,
      "convertToLinearSpace": false,
      "valueType": "number",
      "value": 0.4
    },
    {
      "customType": "BABYLON.ReflectionBlock",
      "id": 165808,
      "name": "Reflection",
      "comments": "",
      "visibleInInspector": false,
      "visibleOnFrame": false,
      "target": 3,
      "inputs": [
        {
          "name": "position",
          "inputName": "position",
          "targetBlockId": 165761,
          "targetConnectionName": "output",
          "isExposedOnFrame": true,
          "exposedPortPosition": -1
        },
        {
          "name": "world",
          "inputName": "world",
          "targetBlockId": 165809,
          "targetConnectionName": "output",
          "isExposedOnFrame": true,
          "exposedPortPosition": -1
        },
        {
          "name": "color",
          "inputName": "color",
          "targetBlockId": 165810,
          "targetConnectionName": "output",
          "isExposedOnFrame": true,
          "exposedPortPosition": -1
        }
      ],
      "outputs": [
        {
          "name": "reflection"
        }
      ],
      "useSphericalHarmonics": true,
      "forceIrradianceInFragment": false,
      "gammaSpace": true
    },
    {
      "customType": "BABYLON.ElbowBlock",
      "id": 165809,
      "name": "",
      "comments": "",
      "visibleInInspector": false,
      "visibleOnFrame": false,
      "target": 1,
      "inputs": [
        {
          "name": "input",
          "inputName": "input",
          "targetBlockId": 165762,
          "targetConnectionName": "output",
          "isExposedOnFrame": true,
          "exposedPortPosition": -1
        }
      ],
      "outputs": [
        {
          "name": "output"
        }
      ]
    },
    {
      "customType": "BABYLON.LerpBlock",
      "id": 165810,
      "name": "Lerp",
      "comments": "",
      "visibleInInspector": false,
      "visibleOnFrame": false,
      "target": 4,
      "inputs": [
        {
          "name": "left",
          "displayName": "left",
          "inputName": "left",
          "targetBlockId": 165811,
          "targetConnectionName": "output",
          "isExposedOnFrame": true,
          "exposedPortPosition": -1
        },
        {
          "name": "right",
          "displayName": "right",
          "inputName": "right",
          "targetBlockId": 165825,
          "targetConnectionName": "output",
          "isExposedOnFrame": true,
          "exposedPortPosition": -1
        },
        {
          "name": "gradient",
          "displayName": "gradient",
          "inputName": "gradient",
          "targetBlockId": 165826,
          "targetConnectionName": "fresnel",
          "isExposedOnFrame": true,
          "exposedPortPosition": -1
        }
      ],
      "outputs": [
        {
          "name": "output",
          "displayName": "output"
        }
      ]
    },
    {
      "customType": "BABYLON.MultiplyBlock",
      "id": 165811,
      "name": "Multiply",
      "comments": "",
      "visibleInInspector": false,
      "visibleOnFrame": false,
      "target": 4,
      "inputs": [
        {
          "name": "left",
          "inputName": "left",
          "targetBlockId": 165812,
          "targetConnectionName": "rgb",
          "isExposedOnFrame": true,
          "exposedPortPosition": -1
        },
        {
          "name": "right",
          "inputName": "right",
          "targetBlockId": 165824,
          "targetConnectionName": "output",
          "isExposedOnFrame": true,
          "exposedPortPosition": -1
        }
      ],
      "outputs": [
        {
          "name": "output"
        }
      ]
    },
    {
      "customType": "BABYLON.TextureBlock",
      "id": 165812,
      "name": "MatCapTexture",
      "comments": "",
      "visibleInInspector": false,
      "visibleOnFrame": false,
      "target": 3,
      "inputs": [
        {
          "name": "uv",
          "inputName": "uv",
          "targetBlockId": 165814,
          "targetConnectionName": "output",
          "isExposedOnFrame": true,
          "exposedPortPosition": -1
        },
        {
          "name": "source"
        }
      ],
      "outputs": [
        {
          "name": "rgba"
        },
        {
          "name": "rgb"
        },
        {
          "name": "r"
        },
        {
          "name": "g"
        },
        {
          "name": "b"
        },
        {
          "name": "a"
        },
        {
          "name": "level"
        }
      ],
      "convertToGammaSpace": false,
      "convertToLinearSpace": false,
      "fragmentOnly": false,
      "disableLevelMultiplication": false,
      "texture": {
        "tags": null,
        "url": "",
        "uOffset": 0,
        "vOffset": 0,
        "uScale": 1,
        "vScale": 1,
        "uAng": 0,
        "vAng": 0,
        "wAng": 0,
        "uRotationCenter": 0.5,
        "vRotationCenter": 0.5,
        "wRotationCenter": 0.5,
        "homogeneousRotationInUVTransform": false,
        "isBlocking": true,
        "name": "data:image/png,iVBORw0KGgoAAAANSUhE_-538443147",
        "hasAlpha": false,
        "getAlphaFromRGB": false,
        "level": 1,
        "coordinatesIndex": 0,
        "optimizeUVAllocation": true,
        "coordinatesMode": 7,
        "wrapU": 1,
        "wrapV": 1,
        "wrapR": 1,
        "anisotropicFilteringLevel": 4,
        "isCube": false,
        "is3D": false,
        "is2DArray": false,
        "gammaSpace": true,
        "invertZ": false,
        "lodLevelInAlpha": false,
        "lodGenerationOffset": 0,
        "lodGenerationScale": 0,
        "linearSpecularLOD": false,
        "isRenderTarget": false,
        "animations": [],
        "invertY": false,
        "samplingMode": 3,
        "_useSRGBBuffer": false
      }
    },
    {
      "customType": "BABYLON.AddBlock",
      "id": 165814,
      "name": "Add",
      "comments": "",
      "visibleInInspector": false,
      "visibleOnFrame": false,
      "target": 4,
      "inputs": [
        {
          "name": "left",
          "displayName": "left",
          "inputName": "left",
          "targetBlockId": 165815,
          "targetConnectionName": "output",
          "isExposedOnFrame": true,
          "exposedPortPosition": -1
        },
        {
          "name": "right",
          "displayName": "right",
          "inputName": "right",
          "targetBlockId": 165823,
          "targetConnectionName": "output",
          "isExposedOnFrame": true,
          "exposedPortPosition": -1
        }
      ],
      "outputs": [
        {
          "name": "output",
          "displayName": "output"
        }
      ]
    },
    {
      "customType": "BABYLON.MultiplyBlock",
      "id": 165815,
      "name": "Multiply",
      "comments": "",
      "visibleInInspector": false,
      "visibleOnFrame": false,
      "target": 4,
      "inputs": [
        {
          "name": "left",
          "displayName": "left",
          "inputName": "left",
          "targetBlockId": 165816,
          "targetConnectionName": "xy",
          "isExposedOnFrame": true,
          "exposedPortPosition": -1
        },
        {
          "name": "right",
          "displayName": "right",
          "inputName": "right",
          "targetBlockId": 165823,
          "targetConnectionName": "output",
          "isExposedOnFrame": true,
          "exposedPortPosition": -1
        }
      ],
      "outputs": [
        {
          "name": "output",
          "displayName": "output"
        }
      ]
    },
    {
      "customType": "BABYLON.VectorSplitterBlock",
      "id": 165816,
      "name": "VectorSplitter",
      "comments": "",
      "visibleInInspector": false,
      "visibleOnFrame": false,
      "target": 4,
      "inputs": [
        {
          "name": "xyzw",
          "displayName": "xyzw",
          "inputName": "xyzw",
          "targetBlockId": 165817,
          "targetConnectionName": "output",
          "isExposedOnFrame": true,
          "exposedPortPosition": -1
        },
        {
          "name": "xyz ",
          "displayName": "xyz "
        },
        {
          "name": "xy ",
          "displayName": "xy "
        }
      ],
      "outputs": [
        {
          "name": "xyz",
          "displayName": "xyz"
        },
        {
          "name": "xy",
          "displayName": "xy"
        },
        {
          "name": "zw",
          "displayName": "zw"
        },
        {
          "name": "x",
          "displayName": "x"
        },
        {
          "name": "y",
          "displayName": "y"
        },
        {
          "name": "z",
          "displayName": "z"
        },
        {
          "name": "w",
          "displayName": "w"
        }
      ]
    },
    {
      "customType": "BABYLON.NormalizeBlock",
      "id": 165817,
      "name": "Normalize",
      "comments": "",
      "visibleInInspector": false,
      "visibleOnFrame": false,
      "target": 4,
      "inputs": [
        {
          "name": "input",
          "displayName": "input",
          "inputName": "input",
          "targetBlockId": 165818,
          "targetConnectionName": "output",
          "isExposedOnFrame": true,
          "exposedPortPosition": -1
        }
      ],
      "outputs": [
        {
          "name": "output",
          "displayName": "output"
        }
      ]
    },
    {
      "customType": "BABYLON.TransformBlock",
      "id": 165818,
      "name": "Transform",
      "comments": "",
      "visibleInInspector": false,
      "visibleOnFrame": false,
      "target": 1,
      "inputs": [
        {
          "name": "vector",
          "displayName": "vector",
          "inputName": "vector",
          "targetBlockId": 165819,
          "targetConnectionName": "output",
          "isExposedOnFrame": true,
          "exposedPortPosition": -1
        },
        {
          "name": "transform",
          "displayName": "transform",
          "inputName": "transform",
          "targetBlockId": 165822,
          "targetConnectionName": "output",
          "isExposedOnFrame": true,
          "exposedPortPosition": -1
        }
      ],
      "outputs": [
        {
          "name": "output",
          "displayName": "output"
        },
        {
          "name": "xyz",
          "displayName": "xyz"
        }
      ],
      "complementZ": 0,
      "complementW": 1
    },
    {
      "customType": "BABYLON.TransformBlock",
      "id": 165819,
      "name": "World normal",
      "comments": "",
      "visibleInInspector": false,
      "visibleOnFrame": false,
      "target": 1,
      "inputs": [
        {
          "name": "vector",
          "displayName": "vector",
          "inputName": "vector",
          "targetBlockId": 165820,
          "targetConnectionName": "output",
          "isExposedOnFrame": true,
          "exposedPortPosition": -1
        },
        {
          "name": "transform",
          "displayName": "transform",
          "inputName": "transform",
          "targetBlockId": 165821,
          "targetConnectionName": "output",
          "isExposedOnFrame": true,
          "exposedPortPosition": -1
        }
      ],
      "outputs": [
        {
          "name": "output",
          "displayName": "output"
        },
        {
          "name": "xyz",
          "displayName": "xyz"
        }
      ],
      "complementZ": 0,
      "complementW": 0
    },
    {
      "customType": "BABYLON.InputBlock",
      "id": 165820,
      "name": "normal",
      "comments": "",
      "visibleInInspector": false,
      "visibleOnFrame": false,
      "target": 1,
      "inputs": [],
      "outputs": [
        {
          "name": "output"
        }
      ],
      "type": 8,
      "mode": 1,
      "animationType": 0,
      "min": 0,
      "max": 0,
      "isBoolean": false,
      "matrixMode": 0,
      "isConstant": false,
      "groupInInspector": "",
      "convertToGammaSpace": false,
      "convertToLinearSpace": false
    },
    {
      "customType": "BABYLON.InputBlock",
      "id": 165821,
      "name": "World",
      "comments": "",
      "visibleInInspector": false,
      "visibleOnFrame": false,
      "target": 1,
      "inputs": [],
      "outputs": [
        {
          "name": "output"
        }
      ],
      "type": 128,
      "mode": 0,
      "systemValue": 1,
      "animationType": 0,
      "min": 0,
      "max": 0,
      "isBoolean": false,
      "matrixMode": 0,
      "isConstant": false,
      "groupInInspector": "",
      "convertToGammaSpace": false,
      "convertToLinearSpace": false
    },
    {
      "customType": "BABYLON.InputBlock",
      "id": 165822,
      "name": "World x View",
      "comments": "",
      "visibleInInspector": false,
      "visibleOnFrame": false,
      "target": 1,
      "inputs": [],
      "outputs": [
        {
          "name": "output"
        }
      ],
      "type": 128,
      "mode": 0,
      "systemValue": 4,
      "animationType": 0,
      "min": 0,
      "max": 0,
      "isBoolean": false,
      "matrixMode": 0,
      "isConstant": false,
      "groupInInspector": "",
      "convertToGammaSpace": false,
      "convertToLinearSpace": false
    },
    {
      "customType": "BABYLON.InputBlock",
      "id": 165823,
      "name": "Vector2",
      "comments": "",
      "visibleInInspector": false,
      "visibleOnFrame": false,
      "target": 1,
      "inputs": [],
      "outputs": [
        {
          "name": "output"
        }
      ],
      "type": 4,
      "mode": 0,
      "animationType": 0,
      "min": 0,
      "max": 0,
      "isBoolean": false,
      "matrixMode": 0,
      "isConstant": false,
      "groupInInspector": "",
      "convertToGammaSpace": false,
      "convertToLinearSpace": false,
      "valueType": "BABYLON.Vector2",
      "value": [
        0.5,
        0.5
      ]
    },
    {
      "customType": "BABYLON.InputBlock",
      "id": 165824,
      "name": "Color3",
      "comments": "",
      "visibleInInspector": false,
      "visibleOnFrame": false,
      "target": 1,
      "inputs": [],
      "outputs": [
        {
          "name": "output"
        }
      ],
      "type": 32,
      "mode": 0,
      "animationType": 0,
      "min": 0,
      "max": 0,
      "isBoolean": false,
      "matrixMode": 0,
      "isConstant": false,
      "groupInInspector": "",
      "convertToGammaSpace": false,
      "convertToLinearSpace": false,
      "valueType": "BABYLON.Color3",
      "value": [
        1,
        1,
        1
      ]
    },
    {
      "customType": "BABYLON.InputBlock",
      "id": 165825,
      "name": "Color3",
      "comments": "",
      "visibleInInspector": false,
      "visibleOnFrame": false,
      "target": 1,
      "inputs": [],
      "outputs": [
        {
          "name": "output"
        }
      ],
      "type": 32,
      "mode": 0,
      "animationType": 0,
      "min": 0,
      "max": 0,
      "isBoolean": false,
      "matrixMode": 0,
      "isConstant": false,
      "groupInInspector": "",
      "convertToGammaSpace": false,
      "convertToLinearSpace": false,
      "valueType": "BABYLON.Color3",
      "value": [
        1,
        1,
        1
      ]
    },
    {
      "customType": "BABYLON.FresnelBlock",
      "id": 165826,
      "name": "Fresnel",
      "comments": "",
      "visibleInInspector": false,
      "visibleOnFrame": false,
      "target": 4,
      "inputs": [
        {
          "name": "worldNormal",
          "displayName": "worldNormal",
          "inputName": "worldNormal",
          "targetBlockId": 165787,
          "targetConnectionName": "output",
          "isExposedOnFrame": true,
          "exposedPortPosition": 0
        },
        {
          "name": "viewDirection",
          "displayName": "viewDirection",
          "inputName": "viewDirection",
          "targetBlockId": 165788,
          "targetConnectionName": "output",
          "isExposedOnFrame": true,
          "exposedPortPosition": 1
        },
        {
          "name": "bias",
          "displayName": "bias",
          "inputName": "bias",
          "targetBlockId": 165827,
          "targetConnectionName": "output",
          "isExposedOnFrame": true,
          "exposedPortPosition": -1
        },
        {
          "name": "power",
          "displayName": "power",
          "inputName": "power",
          "targetBlockId": 165828,
          "targetConnectionName": "output",
          "isExposedOnFrame": true,
          "exposedPortPosition": -1
        }
      ],
      "outputs": [
        {
          "name": "fresnel",
          "displayName": "fresnel"
        }
      ]
    },
    {
      "customType": "BABYLON.InputBlock",
      "id": 165827,
      "name": "MatCap_bias",
      "comments": "",
      "visibleInInspector": true,
      "visibleOnFrame": false,
      "target": 1,
      "inputs": [],
      "outputs": [
        {
          "name": "output"
        }
      ],
      "type": 1,
      "mode": 0,
      "animationType": 0,
      "min": 0,
      "max": 1,
      "isBoolean": false,
      "matrixMode": 0,
      "isConstant": false,
      "groupInInspector": "",
      "convertToGammaSpace": false,
      "convertToLinearSpace": false,
      "valueType": "number",
      "value": 0.3
    },
    {
      "customType": "BABYLON.InputBlock",
      "id": 165828,
      "name": "MatCap_power",
      "comments": "",
      "visibleInInspector": true,
      "visibleOnFrame": false,
      "target": 1,
      "inputs": [],
      "outputs": [
        {
          "name": "output"
        }
      ],
      "type": 1,
      "mode": 0,
      "animationType": 0,
      "min": 0,
      "max": 20,
      "isBoolean": false,
      "matrixMode": 0,
      "isConstant": false,
      "groupInInspector": "",
      "convertToGammaSpace": false,
      "convertToLinearSpace": false,
      "valueType": "number",
      "value": 1.5
    },
    {
      "customType": "BABYLON.ClearCoatBlock",
      "id": 165829,
      "name": "ClearCoatBlock",
      "comments": "",
      "visibleInInspector": false,
      "visibleOnFrame": false,
      "target": 2,
      "inputs": [
        {
          "name": "intensity",
          "inputName": "intensity",
          "targetBlockId": 165830,
          "targetConnectionName": "output",
          "isExposedOnFrame": true,
          "exposedPortPosition": -1
        },
        {
          "name": "roughness",
          "inputName": "roughness",
          "targetBlockId": 165831,
          "targetConnectionName": "output",
          "isExposedOnFrame": true,
          "exposedPortPosition": -1
        },
        {
          "name": "indexOfRefraction",
          "inputName": "indexOfRefraction",
          "targetBlockId": 165832,
          "targetConnectionName": "output",
          "isExposedOnFrame": true,
          "exposedPortPosition": -1
        },
        {
          "name": "normalMapColor"
        },
        {
          "name": "uv"
        },
        {
          "name": "tintColor",
          "inputName": "tintColor",
          "targetBlockId": 165833,
          "targetConnectionName": "output",
          "isExposedOnFrame": true,
          "exposedPortPosition": -1
        },
        {
          "name": "tintAtDistance"
        },
        {
          "name": "tintThickness",
          "inputName": "tintThickness",
          "targetBlockId": 165844,
          "targetConnectionName": "output",
          "isExposedOnFrame": true,
          "exposedPortPosition": -1
        },
        {
          "name": "worldTangent"
        },
        {
          "name": "worldNormal"
        },
        {
          "name": "TBN"
        }
      ],
      "outputs": [
        {
          "name": "clearcoat"
        }
      ],
      "remapF0OnInterfaceChange": true
    },
    {
      "customType": "BABYLON.InputBlock",
      "id": 165830,
      "name": "ClearCoat intensity",
      "comments": "",
      "visibleInInspector": false,
      "visibleOnFrame": false,
      "target": 2,
      "inputs": [],
      "outputs": [
        {
          "name": "output"
        }
      ],
      "type": 1,
      "mode": 0,
      "animationType": 0,
      "min": 0,
      "max": 1,
      "isBoolean": false,
      "matrixMode": 0,
      "isConstant": false,
      "groupInInspector": "",
      "convertToGammaSpace": false,
      "convertToLinearSpace": false,
      "valueType": "number",
      "value": 1
    },
    {
      "customType": "BABYLON.InputBlock",
      "id": 165831,
      "name": "Roughness",
      "comments": "",
      "visibleInInspector": false,
      "visibleOnFrame": false,
      "target": 1,
      "inputs": [],
      "outputs": [
        {
          "name": "output"
        }
      ],
      "type": 1,
      "mode": 0,
      "animationType": 0,
      "min": 0,
      "max": 1,
      "isBoolean": false,
      "matrixMode": 0,
      "isConstant": false,
      "groupInInspector": "",
      "convertToGammaSpace": false,
      "convertToLinearSpace": false,
      "valueType": "number",
      "value": 1
    },
    {
      "customType": "BABYLON.InputBlock",
      "id": 165832,
      "name": "Float",
      "comments": "",
      "visibleInInspector": false,
      "visibleOnFrame": false,
      "target": 1,
      "inputs": [],
      "outputs": [
        {
          "name": "output"
        }
      ],
      "type": 1,
      "mode": 0,
      "animationType": 0,
      "min": 0,
      "max": 2,
      "isBoolean": false,
      "matrixMode": 0,
      "isConstant": false,
      "groupInInspector": "",
      "convertToGammaSpace": false,
      "convertToLinearSpace": false,
      "valueType": "number",
      "value": 1.5
    },
    {
      "customType": "BABYLON.LerpBlock",
      "id": 165833,
      "name": "Lerp",
      "comments": "",
      "visibleInInspector": false,
      "visibleOnFrame": false,
      "target": 4,
      "inputs": [
        {
          "name": "left",
          "displayName": "left",
          "inputName": "left",
          "targetBlockId": 165834,
          "targetConnectionName": "output",
          "isExposedOnFrame": true,
          "exposedPortPosition": -1
        },
        {
          "name": "right",
          "displayName": "right",
          "inputName": "right",
          "targetBlockId": 165835,
          "targetConnectionName": "rgb",
          "isExposedOnFrame": true,
          "exposedPortPosition": 0
        },
        {
          "name": "gradient",
          "displayName": "gradient",
          "inputName": "gradient",
          "targetBlockId": 165843,
          "targetConnectionName": "output",
          "isExposedOnFrame": true,
          "exposedPortPosition": -1
        }
      ],
      "outputs": [
        {
          "name": "output",
          "displayName": "output"
        }
      ]
    },
    {
      "customType": "BABYLON.InputBlock",
      "id": 165834,
      "name": "Color3",
      "comments": "",
      "visibleInInspector": false,
      "visibleOnFrame": false,
      "target": 1,
      "inputs": [],
      "outputs": [
        {
          "name": "output"
        }
      ],
      "type": 32,
      "mode": 0,
      "animationType": 0,
      "min": 0,
      "max": 0,
      "isBoolean": false,
      "matrixMode": 0,
      "isConstant": false,
      "groupInInspector": "",
      "convertToGammaSpace": false,
      "convertToLinearSpace": false,
      "valueType": "BABYLON.Color3",
      "value": [
        2.3,
        2.3,
        2.3
      ]
    },
    {
      "customType": "BABYLON.ReflectionTextureBlock",
      "id": 165835,
      "name": "Reflection texture",
      "comments": "",
      "visibleInInspector": false,
      "visibleOnFrame": false,
      "target": 3,
      "inputs": [
        {
          "name": "position",
          "inputName": "position",
          "targetBlockId": 165837,
          "targetConnectionName": "output",
          "isExposedOnFrame": true,
          "exposedPortPosition": -1
        },
        {
          "name": "worldPosition",
          "inputName": "worldPosition",
          "targetBlockId": 165838,
          "targetConnectionName": "output",
          "isExposedOnFrame": true,
          "exposedPortPosition": -1
        },
        {
          "name": "worldNormal",
          "inputName": "worldNormal",
          "targetBlockId": 165839,
          "targetConnectionName": "output",
          "isExposedOnFrame": true,
          "exposedPortPosition": -1
        },
        {
          "name": "world",
          "inputName": "world",
          "targetBlockId": 165840,
          "targetConnectionName": "output",
          "isExposedOnFrame": true,
          "exposedPortPosition": -1
        },
        {
          "name": "cameraPosition",
          "inputName": "cameraPosition",
          "targetBlockId": 165841,
          "targetConnectionName": "output",
          "isExposedOnFrame": true,
          "exposedPortPosition": -1
        },
        {
          "name": "view",
          "inputName": "view",
          "targetBlockId": 165842,
          "targetConnectionName": "output",
          "isExposedOnFrame": true,
          "exposedPortPosition": -1
        }
      ],
      "outputs": [
        {
          "name": "rgb"
        },
        {
          "name": "rgba"
        },
        {
          "name": "r"
        },
        {
          "name": "g"
        },
        {
          "name": "b"
        },
        {
          "name": "a"
        }
      ],
      "texture": {
        "tags": null,
        "url": "",
        "uOffset": 0,
        "vOffset": 0,
        "uScale": 1,
        "vScale": 1,
        "uAng": 0,
        "vAng": 0,
        "wAng": 0,
        "uRotationCenter": 0.5,
        "vRotationCenter": 0.5,
        "wRotationCenter": 0.5,
        "homogeneousRotationInUVTransform": false,
        "isBlocking": true,
        "name": "data:image/png,iVBORw0KGgoAAAANSUhE_1207321015",
        "hasAlpha": false,
        "getAlphaFromRGB": false,
        "level": 1,
        "coordinatesIndex": 0,
        "optimizeUVAllocation": true,
        "coordinatesMode": 7,
        "wrapU": 1,
        "wrapV": 1,
        "wrapR": 1,
        "anisotropicFilteringLevel": 4,
        "isCube": false,
        "is3D": false,
        "is2DArray": false,
        "gammaSpace": true,
        "invertZ": false,
        "lodLevelInAlpha": false,
        "lodGenerationOffset": 0,
        "lodGenerationScale": 0,
        "linearSpecularLOD": false,
        "isRenderTarget": false,
        "animations": [],
        "invertY": true,
        "samplingMode": 1,
        "_useSRGBBuffer": false
      }
    },
    {
      "customType": "BABYLON.ElbowBlock",
      "id": 165837,
      "name": "",
      "comments": "",
      "visibleInInspector": false,
      "visibleOnFrame": false,
      "target": 1,
      "inputs": [
        {
          "name": "input",
          "inputName": "input",
          "targetBlockId": 165761,
          "targetConnectionName": "output",
          "isExposedOnFrame": true,
          "exposedPortPosition": -1
        }
      ],
      "outputs": [
        {
          "name": "output"
        }
      ]
    },
    {
      "customType": "BABYLON.ElbowBlock",
      "id": 165838,
      "name": "",
      "comments": "",
      "visibleInInspector": false,
      "visibleOnFrame": false,
      "target": 1,
      "inputs": [
        {
          "name": "input",
          "inputName": "input",
          "targetBlockId": 165760,
          "targetConnectionName": "output",
          "isExposedOnFrame": true,
          "exposedPortPosition": -1
        }
      ],
      "outputs": [
        {
          "name": "output"
        }
      ]
    },
    {
      "customType": "BABYLON.ElbowBlock",
      "id": 165839,
      "name": "",
      "comments": "",
      "visibleInInspector": false,
      "visibleOnFrame": false,
      "target": 1,
      "inputs": [
        {
          "name": "input",
          "inputName": "input",
          "targetBlockId": 165768,
          "targetConnectionName": "output",
          "isExposedOnFrame": true,
          "exposedPortPosition": -1
        }
      ],
      "outputs": [
        {
          "name": "output"
        }
      ]
    },
    {
      "customType": "BABYLON.ElbowBlock",
      "id": 165840,
      "name": "",
      "comments": "",
      "visibleInInspector": false,
      "visibleOnFrame": false,
      "target": 1,
      "inputs": [
        {
          "name": "input",
          "inputName": "input",
          "targetBlockId": 165762,
          "targetConnectionName": "output",
          "isExposedOnFrame": true,
          "exposedPortPosition": -1
        }
      ],
      "outputs": [
        {
          "name": "output"
        }
      ]
    },
    {
      "customType": "BABYLON.ElbowBlock",
      "id": 165841,
      "name": "",
      "comments": "",
      "visibleInInspector": false,
      "visibleOnFrame": false,
      "target": 1,
      "inputs": [
        {
          "name": "input",
          "inputName": "input",
          "targetBlockId": 165772,
          "targetConnectionName": "output",
          "isExposedOnFrame": true,
          "exposedPortPosition": -1
        }
      ],
      "outputs": [
        {
          "name": "output"
        }
      ]
    },
    {
      "customType": "BABYLON.ElbowBlock",
      "id": 165842,
      "name": "",
      "comments": "",
      "visibleInInspector": false,
      "visibleOnFrame": false,
      "target": 1,
      "inputs": [
        {
          "name": "input",
          "inputName": "input",
          "targetBlockId": 165771,
          "targetConnectionName": "output",
          "isExposedOnFrame": true,
          "exposedPortPosition": -1
        }
      ],
      "outputs": [
        {
          "name": "output"
        }
      ]
    },
    {
      "customType": "BABYLON.InputBlock",
      "id": 165843,
      "name": "Blend_Alpha",
      "comments": "",
      "visibleInInspector": true,
      "visibleOnFrame": false,
      "target": 1,
      "inputs": [],
      "outputs": [
        {
          "name": "output"
        }
      ],
      "type": 32,
      "mode": 0,
      "animationType": 0,
      "min": 0,
      "max": 0,
      "isBoolean": false,
      "matrixMode": 0,
      "isConstant": false,
      "groupInInspector": "",
      "convertToGammaSpace": false,
      "convertToLinearSpace": false,
      "valueType": "BABYLON.Color3",
      "value": [
        0.6,
        0.6,
        0.6
      ]
    },
    {
      "customType": "BABYLON.InputBlock",
      "id": 165844,
      "name": "tintThickness",
      "comments": "",
      "visibleInInspector": true,
      "visibleOnFrame": false,
      "target": 1,
      "inputs": [],
      "outputs": [
        {
          "name": "output"
        }
      ],
      "type": 1,
      "mode": 0,
      "animationType": 0,
      "min": 0,
      "max": 1,
      "isBoolean": false,
      "matrixMode": 0,
      "isConstant": false,
      "groupInInspector": "",
      "convertToGammaSpace": false,
      "convertToLinearSpace": false,
      "valueType": "number",
      "value": 0.8
    },
    {
      "customType": "BABYLON.MultiplyBlock",
      "id": 165845,
      "name": "Multiply",
      "comments": "",
      "visibleInInspector": false,
      "visibleOnFrame": false,
      "target": 4,
      "inputs": [
        {
          "name": "left",
          "displayName": "left",
          "inputName": "left",
          "targetBlockId": 165767,
          "targetConnectionName": "lighting",
          "isExposedOnFrame": true,
          "exposedPortPosition": 6
        },
        {
          "name": "right",
          "displayName": "right",
          "inputName": "right",
          "targetBlockId": 165846,
          "targetConnectionName": "output",
          "isExposedOnFrame": true,
          "exposedPortPosition": -1
        }
      ],
      "outputs": [
        {
          "name": "output",
          "displayName": "output"
        }
      ]
    },
    {
      "customType": "BABYLON.MultiplyBlock",
      "id": 165846,
      "name": "Multiply",
      "comments": "",
      "visibleInInspector": false,
      "visibleOnFrame": false,
      "target": 4,
      "inputs": [
        {
          "name": "left",
          "displayName": "left",
          "inputName": "left",
          "targetBlockId": 165847,
          "targetConnectionName": "rgb",
          "isExposedOnFrame": true,
          "exposedPortPosition": -1
        },
        {
          "name": "right",
          "displayName": "right",
          "inputName": "right",
          "targetBlockId": 165850,
          "targetConnectionName": "xyz",
          "isExposedOnFrame": true,
          "exposedPortPosition": -1
        }
      ],
      "outputs": [
        {
          "name": "output",
          "displayName": "output"
        }
      ]
    },
    {
      "customType": "BABYLON.ReflectionTextureBlock",
      "id": 165847,
      "name": "Reflection texture",
      "comments": "",
      "visibleInInspector": false,
      "visibleOnFrame": false,
      "target": 3,
      "inputs": [
        {
          "name": "position",
          "displayName": "position",
          "inputName": "position",
          "targetBlockId": 165837,
          "targetConnectionName": "output",
          "isExposedOnFrame": true,
          "exposedPortPosition": 0
        },
        {
          "name": "worldPosition",
          "displayName": "worldPosition",
          "inputName": "worldPosition",
          "targetBlockId": 165838,
          "targetConnectionName": "output",
          "isExposedOnFrame": true,
          "exposedPortPosition": 1
        },
        {
          "name": "worldNormal",
          "displayName": "worldNormal",
          "inputName": "worldNormal",
          "targetBlockId": 165839,
          "targetConnectionName": "output",
          "isExposedOnFrame": true,
          "exposedPortPosition": 2
        },
        {
          "name": "world",
          "displayName": "world",
          "inputName": "world",
          "targetBlockId": 165809,
          "targetConnectionName": "output",
          "isExposedOnFrame": true,
          "exposedPortPosition": 3
        },
        {
          "name": "cameraPosition",
          "displayName": "cameraPosition",
          "inputName": "cameraPosition",
          "targetBlockId": 165849,
          "targetConnectionName": "output",
          "isExposedOnFrame": true,
          "exposedPortPosition": -1
        },
        {
          "name": "view",
          "displayName": "view",
          "inputName": "view",
          "targetBlockId": 165842,
          "targetConnectionName": "output",
          "isExposedOnFrame": true,
          "exposedPortPosition": 4
        }
      ],
      "outputs": [
        {
          "name": "rgb",
          "displayName": "rgb"
        },
        {
          "name": "rgba",
          "displayName": "rgba"
        },
        {
          "name": "r",
          "displayName": "r"
        },
        {
          "name": "g",
          "displayName": "g"
        },
        {
          "name": "b",
          "displayName": "b"
        },
        {
          "name": "a",
          "displayName": "a"
        }
      ],
      "texture": {
        "tags": null,
        "url": "",
        "uOffset": 0,
        "vOffset": 0,
        "uScale": 1,
        "vScale": 1,
        "uAng": 0,
        "vAng": 0,
        "wAng": 0,
        "uRotationCenter": 0.5,
        "vRotationCenter": 0.5,
        "wRotationCenter": 0.5,
        "homogeneousRotationInUVTransform": false,
        "isBlocking": true,
        "name": "data:image/png,iVBORw0KGgoAAAANSUhE_706992165",
        "hasAlpha": false,
        "getAlphaFromRGB": false,
        "level": 1,
        "coordinatesIndex": 0,
        "optimizeUVAllocation": true,
        "coordinatesMode": 7,
        "wrapU": 1,
        "wrapV": 1,
        "wrapR": 1,
        "anisotropicFilteringLevel": 4,
        "isCube": false,
        "is3D": false,
        "is2DArray": false,
        "gammaSpace": true,
        "invertZ": false,
        "lodLevelInAlpha": false,
        "lodGenerationOffset": 0,
        "lodGenerationScale": 0,
        "linearSpecularLOD": false,
        "isRenderTarget": false,
        "animations": [],
        "invertY": true,
        "samplingMode": 3,
        "_useSRGBBuffer": false
      }
    },
    {
      "customType": "BABYLON.InputBlock",
      "id": 165849,
      "name": "cameraPosition",
      "comments": "",
      "visibleInInspector": false,
      "visibleOnFrame": false,
      "target": 1,
      "inputs": [],
      "outputs": [
        {
          "name": "output"
        }
      ],
      "type": 8,
      "mode": 0,
      "systemValue": 7,
      "animationType": 0,
      "min": 0,
      "max": 0,
      "isBoolean": false,
      "matrixMode": 0,
      "isConstant": false,
      "groupInInspector": "",
      "convertToGammaSpace": false,
      "convertToLinearSpace": false
    },
    {
      "customType": "BABYLON.VectorMergerBlock",
      "id": 165850,
      "name": "VectorMerger",
      "comments": "",
      "visibleInInspector": false,
      "visibleOnFrame": false,
      "target": 4,
      "inputs": [
        {
          "name": "xyzw "
        },
        {
          "name": "xyz "
        },
        {
          "name": "xy "
        },
        {
          "name": "zw "
        },
        {
          "name": "x",
          "inputName": "x",
          "targetBlockId": 165851,
          "targetConnectionName": "output",
          "isExposedOnFrame": true,
          "exposedPortPosition": -1
        },
        {
          "name": "y",
          "inputName": "y",
          "targetBlockId": 165851,
          "targetConnectionName": "output",
          "isExposedOnFrame": true,
          "exposedPortPosition": -1
        },
        {
          "name": "z",
          "inputName": "z",
          "targetBlockId": 165851,
          "targetConnectionName": "output",
          "isExposedOnFrame": true,
          "exposedPortPosition": -1
        },
        {
          "name": "w"
        }
      ],
      "outputs": [
        {
          "name": "xyzw"
        },
        {
          "name": "xyz"
        },
        {
          "name": "xy"
        },
        {
          "name": "zw"
        }
      ],
      "xSwizzle": "x",
      "ySwizzle": "y",
      "zSwizzle": "z",
      "wSwizzle": "w"
    },
    {
      "customType": "BABYLON.InputBlock",
      "id": 165851,
      "name": "Higlight",
      "comments": "",
      "visibleInInspector": true,
      "visibleOnFrame": false,
      "target": 1,
      "inputs": [],
      "outputs": [
        {
          "name": "output"
        }
      ],
      "type": 1,
      "mode": 0,
      "animationType": 0,
      "min": 0,
      "max": 2,
      "isBoolean": false,
      "matrixMode": 0,
      "isConstant": false,
      "groupInInspector": "",
      "convertToGammaSpace": false,
      "convertToLinearSpace": false,
      "valueType": "number",
      "value": 0.4
    }
  ]
}